{
  "exclude": [
    "**/bin",
    "**/bower_components",
    "**/jspm_packages",
    "**/node_modules",
    "**/obj",
    "**/platforms"
  ],
  "modules": [
    {
      "name": "图像标注",
      "assemblyFile": "ArtificialIntelligenceStudioClient.Modules.ImageAnnotation.dll",
      "moduleType": "ArtificialIntelligenceStudioClient.Modules.ImageAnnotation.ImageAnnotationModule, ArtificialIntelligenceStudioClient.Modules.ImageAnnotation, Version=1.0.0.0, Culture=neutral, PublicKeyToken=null",
      "moduleName": "图像标注",
      "startupLoaded": false
    }
  ]
}
